[
	{
		"orden":"001-3001",
		"fecha": "12/12/2024",
		"total":5000,
		"detalle":[
			{
				"item":"Iphone 15",
				"precio":2000,
				"cantidad":2
			},
			{
				"item":"Iphone 15",
				"precio":1000,
				"cantidad":1
			}
		]
	}
	,
	{
		"orden":"001-3002",
		"fecha": "12/12/2024",
		"total":4000,
		"detalle":[
			{
				"item":"Iphone 15",
				"precio":2000,
				"cantidad":1
			},
			{
				"item":"Iphone 15",
				"precio":1000,
				"cantidad":2
			}
		]
	}
]
